datasets_from_pdfs/__init__.py
datasets_from_pdfs/build_dictionary.py
datasets_from_pdfs/readpdf.py
pdf2dataset/__init__.py
pdf2dataset/build_dictionary.py
pdf2dataset/readpdf.py
datasets_from_pdfs-0.0.7.dist-info/LICENSE
datasets_from_pdfs-0.0.7.dist-info/METADATA
datasets_from_pdfs-0.0.7.dist-info/WHEEL
datasets_from_pdfs-0.0.7.dist-info/entry_points.txt
datasets_from_pdfs-0.0.7.dist-info/top_level.txt
datasets_from_pdfs-0.0.7.dist-info/RECORD
