Metadata-Version: 2.1
Name: datasets-from-pdfs
Version: 0.0.7
Summary: ('A tool to convert single or mass PDFs to datasets for', 'language analysis, including a toolbox of text and NLP pre-processing options')
Home-page: https://github.com/danieljwhitten/datasets-from-pdfs
Author: Daniel Whitten
Author-email: danieljwhitten@gmail.com
License: UNKNOWN
Platform: UNKNOWN
Classifier: Programming Language :: Python :: 3
Classifier: License :: OSI Approved :: GNU General Public License v3 or later (GPLv3+) 
Classifier: Operating System :: OS Independent
Requires-Python: >=3.6
